cluster/__init__.py
cluster/aggregate_analysis.py
cluster/auto_stack_collector.py
cluster/distributed_coordinator.py
cluster/flamegraph.pl
cluster/gx_0.5.5-1_amd64.deb
cluster/log_monitor_daemon.py
cluster/node_agent.py
cluster/process_processor.py
cluster/pstack
cluster/stack_processor.py
cluster/sysom_hang_analyzer.py
cluster/trigger_distributed_collection.py
sysom_hang_analyzer-1.0.16.data/scripts/flamegraph.pl
sysom_hang_analyzer-1.0.16.data/scripts/pstack
sysom_hang_analyzer-1.0.16.dist-info/METADATA
sysom_hang_analyzer-1.0.16.dist-info/WHEEL
sysom_hang_analyzer-1.0.16.dist-info/entry_points.txt
sysom_hang_analyzer-1.0.16.dist-info/top_level.txt
sysom_hang_analyzer-1.0.16.dist-info/RECORD
